obonetx/__init__.py
obonetx/ontology.py
obonetx-0.3.dist-info/LICENSE
obonetx-0.3.dist-info/METADATA
obonetx-0.3.dist-info/WHEEL
obonetx-0.3.dist-info/top_level.txt
obonetx-0.3.dist-info/RECORD
