Metadata-Version: 2.1
Name: obonetx
Version: 0.3
Summary: An Intuitive Way to Parse and Use Obo-Formatted Ontologies
Home-page: https://github.com/kingmanzhang/obonetx
Author: Xingmin (Aaron) Zhang
Author-email: kingmanzhang@gmail.com
License: CC0 1.0
Keywords: obo ontology networkx parser network obonet
Platform: UNKNOWN
Classifier: Intended Audience :: Science/Research
Classifier: Topic :: Scientific/Engineering :: Bio-Informatics
Classifier: Topic :: Scientific/Engineering :: Information Analysis
Classifier: License :: CC0 1.0 Universal (CC0 1.0) Public Domain Dedication
Classifier: Programming Language :: Python :: 3
Requires-Dist: networkx
Requires-Dist: obonet
Provides-Extra: dev
Requires-Dist: pytest (>=3.7) ; extra == 'dev'
Requires-Dist: twine ; extra == 'dev'
